{
    "category": "Kurti Set",
    "design_code": "Unknown",
    "product_title": "Powder Blue Embroidered Kurti Set with Dupatta",
    "short_description": "Elegant powder blue kurti set with delicate embroidery and matching dupatta. Perfect for festive occasions and special events.",
    "attributes": {
        "color": "Powder Blue",
        "fabric": "Georgette",
        "pattern": "Embroidered",
        "occasion": "Festive"
    },
    "tags": [
        "Kurti Set",
        "Powder Blue",
        "Embroidered",
        "Festive Wear",
        "Indian Ethnic Wear"
    ],
    "s3_images": [
        "https://bisen-enterprise-assets-v1.s3.ap-south-1.amazonaws.com/Kurti_Set/Unknown_1770055449/pose_1.jpg"
    ]
}